{
  "saved_at": "2026-06-04T14:20:42",
  "signature": [
    "2026-06-04",
    1780582584.819,
    1780582111.287
  ],
  "learning_status": {
    "trained": true,
    "samples": 6660,
    "stock_samples": 6660,
    "imported_ai_samples": 499,
    "sector_samples": 0,
    "active_feature_count": 16,
    "recency_weighting_active": true,
    "accuracy_pct": 58.88,
    "validation_accuracy_pct": 58.88,
    "training_accuracy_pct": 60.48,
    "last_trained": "2026-06-04T14:16",
    "source": "stock_feedback",
    "message": "Model trained on 6660 samples.",
    "regime_encoder": {
      "UNKNOWN": 0,
      "HIGH VOLATILITY / CHOPPY": 1,
      "RANGING": 2,
      "TRENDING DOWN": 3
    },
    "sector_encoder": {
      "UNKNOWN": 0,
      "AUTO": 1,
      "BANKING": 2,
      "CAPITAL_GOODS": 3,
      "CHEMICAL": 4,
      "CONSUMER_DURABLES": 5,
      "DEFENCE": 6,
      "ENERGY": 7,
      "FMCG": 8,
      "INFRA": 9,
      "IT": 10,
      "METAL": 11,
      "NBFC_FINANCE": 12,
      "PHARMA": 13,
      "PSU": 14,
      "RAILWAY": 15,
      "REALTY": 16,
      "TELECOM": 17,
      "UNMAPPED": 18
    },
    "feature_encoders": {
      "conviction_tier": {
        "UNKNOWN": 0,
        "HIGH": 1,
        "LOW": 2,
        "MEDIUM": 3,
        "RANGE-BOUND SETUP": 4,
        "VERY_HIGH": 5
      },
      "mode": {
        "UNKNOWN": 0,
        "M0": 1,
        "M2": 2,
        "M3": 3,
        "M4": 4,
        "M5": 5,
        "M6": 6,
        "M7": 7
      },
      "import_source": {
        "UNKNOWN": 0,
        "A-I-L IN ONE": 1,
        "A-I-L IN ONE - FINAL AURA VERDICT": 2,
        "LIVE BREAKOUT PULSE TOP 3": 3,
        "LIVE BREAKOUT PULSE TOP 3 | MODE 2 TOP 3 | MODE 3 TOP 3": 4,
        "MODE 1 TOP 3": 5,
        "MODE 1 TOP 3 | MODE 2 TOP 3": 6,
        "MODE 1 TOP 3 | MODE 2 TOP 3 | MODE 3 TOP 3": 7,
        "MODE 1 TOP 3 | MODE 2 TOP 3 | MODE 3 TOP 3 | TOMORROW'S PICKS - RELAX": 8,
        "MODE 1 TOP 3 | MODE 2 TOP 3 | TOMORROW'S PICKS - RELAX": 9,
        "MODE 1 TOP 3 | MODE 3 TOP 3": 10,
        "MODE 1 TOP 3 | TOMORROW'S PICKS - RELAX": 11,
        "MODE 2 TOP 3": 12,
        "MODE 2 TOP 3 | MODE 3 TOP 3": 13,
        "MODE 2 TOP 3 | MODE 3 TOP 3 | LIVE BREAKOUT PULSE TOP 3": 14,
        "MODE 2 TOP 3 | MODE 3 TOP 3 | MODE 1 TOP 3": 15,
        "MODE 2 TOP 3 | TOMORROW'S PICKS - SWING": 16,
        "MODE 3 TOP 3": 17,
        "MODE 3 TOP 3 | LIVE BREAKOUT PULSE TOP 3": 18,
        "MODE 3 TOP 3 | LIVE BREAKOUT PULSE TOP 3 | MODE 2 TOP 3": 19,
        "MODE 3 TOP 3 | MODE 6 TOP 3": 20,
        "MODE 3 TOP 3 | TOMORROW'S PICKS - INTRADAY": 21,
        "MODE 3 TOP 3 | TOMORROW'S PICKS - MOMENTUM": 22,
        "MODE 3 TOP 3 | TOMORROW'S PICKS - RELAX": 23,
        "MODE 5 TOP 3": 24,
        "MODE 6 TOP 3": 25,
        "MODE 6 TOP 3 | MODE 3 TOP 3": 26,
        "TOMORROW'S PICKS - BREAKOUT": 27,
        "TOMORROW'S PICKS - BREAKOUT | TOMORROW'S PICKS - MOMENTUM": 28,
        "TOMORROW'S PICKS - INTRADAY": 29,
        "TOMORROW'S PICKS - INTRADAY | TOMORROW'S PICKS - SWING": 30,
        "TOMORROW'S PICKS - MOMENTUM": 31,
        "TOMORROW'S PICKS - RELAX": 32,
        "TOMORROW'S PICKS - SWING": 33,
        "TOMORROW'S PICKS - SWING | TOMORROW'S PICKS - RELAX": 34
      },
      "import_category": {
        "UNKNOWN": 0,
        "BREAKOUT": 1,
        "BREAKOUT PULSE": 2,
        "BREAKOUT PULSE | SWING | INTRADAY": 3,
        "BREAKOUT | MOMENTUM": 4,
        "INTRADAY": 5,
        "INTRADAY | BREAKOUT PULSE": 6,
        "INTRADAY | BREAKOUT PULSE | SWING": 7,
        "INTRADAY | RELAX": 8,
        "INTRADAY | SWING": 9,
        "MASTER RANKING": 10,
        "MOMENTUM": 11,
        "MOMENTUM | BREAKOUT PULSE": 12,
        "RELAX": 13,
        "RELAX | MOMENTUM": 14,
        "RELAX | SWING": 15,
        "RELAX | SWING | INTRADAY": 16,
        "RELAX | SWING | MOMENTUM": 17,
        "SWING": 18,
        "SWING | INTRADAY": 19,
        "SWING | INTRADAY | BREAKOUT PULSE": 20,
        "SWING | INTRADAY | RELAX": 21,
        "SWING | MOMENTUM": 22,
        "SWING | RELAX": 23
      },
      "strategy_strip": {
        "UNKNOWN": 0,
        "BREAKOUT": 1,
        "INTRADAY": 2,
        "MOMENTUM": 3,
        "RELAX": 4,
        "SWING": 5
      },
      "source_mode": {
        "UNKNOWN": 0,
        "AI": 1,
        "MANUAL": 2
      },
      "trap_risk": {
        "UNKNOWN": 0,
        "HIGH": 1,
        "LOW": 2,
        "MEDIUM": 3
      },
      "market_bias": {
        "UNKNOWN": 0,
        "BEARISH BIAS": 1,
        "SIDEWAYS / NO EDGE": 2
      },
      "regime": {
        "UNKNOWN": 0,
        "HIGH VOLATILITY / CHOPPY": 1,
        "RANGING": 2,
        "TRENDING DOWN": 3
      },
      "sector": {
        "UNKNOWN": 0,
        "AUTO": 1,
        "BANKING": 2,
        "CAPITAL_GOODS": 3,
        "CHEMICAL": 4,
        "CONSUMER_DURABLES": 5,
        "DEFENCE": 6,
        "ENERGY": 7,
        "FMCG": 8,
        "INFRA": 9,
        "IT": 10,
        "METAL": 11,
        "NBFC_FINANCE": 12,
        "PHARMA": 13,
        "PSU": 14,
        "RAILWAY": 15,
        "REALTY": 16,
        "TELECOM": 17,
        "UNMAPPED": 18
      }
    },
    "validated_today": 0,
    "sector_validated_today": 0,
    "feedback_summary": {
      "total_logged": 6660,
      "rows_with_outcome": 6660,
      "accuracy_pct": 53.57,
      "bullish_precision_pct": 38.72,
      "bearish_precision_pct": 59.51,
      "false_bullish_pct": 61.28,
      "false_bearish_pct": 40.49
    },
    "brain_status": {
      "started_at": "2026-06-04T14:16:15",
      "completed_at": "2026-06-04T14:20:27",
      "feedback": {
        "filled_stock": 0,
        "filled_sector": 0,
        "pending_stock": 0,
        "pending_sector": 8,
        "message": "\u2705 Closed feedback loop: 0 outcomes filled"
      },
      "feedback_summary": {
        "total_logged": 6660,
        "rows_with_outcome": 6660,
        "accuracy_pct": 53.57,
        "bullish_precision_pct": 38.72,
        "bearish_precision_pct": 59.51,
        "false_bullish_pct": 61.28,
        "false_bearish_pct": 40.49
      },
      "meta_model": {
        "trained": true,
        "samples": 6660,
        "stock_samples": 6660,
        "imported_ai_samples": 499,
        "sector_samples": 0,
        "active_feature_count": 16,
        "recency_weighting_active": true,
        "accuracy_pct": 58.88,
        "validation_accuracy_pct": 58.88,
        "training_accuracy_pct": 60.48,
        "last_trained": "2026-06-04T14:16",
        "source": "stock_feedback",
        "message": "Model trained on 6660 samples.",
        "regime_encoder": {
          "UNKNOWN": 0,
          "HIGH VOLATILITY / CHOPPY": 1,
          "RANGING": 2,
          "TRENDING DOWN": 3
        },
        "sector_encoder": {
          "UNKNOWN": 0,
          "AUTO": 1,
          "BANKING": 2,
          "CAPITAL_GOODS": 3,
          "CHEMICAL": 4,
          "CONSUMER_DURABLES": 5,
          "DEFENCE": 6,
          "ENERGY": 7,
          "FMCG": 8,
          "INFRA": 9,
          "IT": 10,
          "METAL": 11,
          "NBFC_FINANCE": 12,
          "PHARMA": 13,
          "PSU": 14,
          "RAILWAY": 15,
          "REALTY": 16,
          "TELECOM": 17,
          "UNMAPPED": 18
        },
        "feature_encoders": {
          "conviction_tier": {
            "UNKNOWN": 0,
            "HIGH": 1,
            "LOW": 2,
            "MEDIUM": 3,
            "RANGE-BOUND SETUP": 4,
            "VERY_HIGH": 5
          },
          "mode": {
            "UNKNOWN": 0,
            "M0": 1,
            "M2": 2,
            "M3": 3,
            "M4": 4,
            "M5": 5,
            "M6": 6,
            "M7": 7
          },
          "import_source": {
            "UNKNOWN": 0,
            "A-I-L IN ONE": 1,
            "A-I-L IN ONE - FINAL AURA VERDICT": 2,
            "LIVE BREAKOUT PULSE TOP 3": 3,
            "LIVE BREAKOUT PULSE TOP 3 | MODE 2 TOP 3 | MODE 3 TOP 3": 4,
            "MODE 1 TOP 3": 5,
            "MODE 1 TOP 3 | MODE 2 TOP 3": 6,
            "MODE 1 TOP 3 | MODE 2 TOP 3 | MODE 3 TOP 3": 7,
            "MODE 1 TOP 3 | MODE 2 TOP 3 | MODE 3 TOP 3 | TOMORROW'S PICKS - RELAX": 8,
            "MODE 1 TOP 3 | MODE 2 TOP 3 | TOMORROW'S PICKS - RELAX": 9,
            "MODE 1 TOP 3 | MODE 3 TOP 3": 10,
            "MODE 1 TOP 3 | TOMORROW'S PICKS - RELAX": 11,
            "MODE 2 TOP 3": 12,
            "MODE 2 TOP 3 | MODE 3 TOP 3": 13,
            "MODE 2 TOP 3 | MODE 3 TOP 3 | LIVE BREAKOUT PULSE TOP 3": 14,
            "MODE 2 TOP 3 | MODE 3 TOP 3 | MODE 1 TOP 3": 15,
            "MODE 2 TOP 3 | TOMORROW'S PICKS - SWING": 16,
            "MODE 3 TOP 3": 17,
            "MODE 3 TOP 3 | LIVE BREAKOUT PULSE TOP 3": 18,
            "MODE 3 TOP 3 | LIVE BREAKOUT PULSE TOP 3 | MODE 2 TOP 3": 19,
            "MODE 3 TOP 3 | MODE 6 TOP 3": 20,
            "MODE 3 TOP 3 | TOMORROW'S PICKS - INTRADAY": 21,
            "MODE 3 TOP 3 | TOMORROW'S PICKS - MOMENTUM": 22,
            "MODE 3 TOP 3 | TOMORROW'S PICKS - RELAX": 23,
            "MODE 5 TOP 3": 24,
            "MODE 6 TOP 3": 25,
            "MODE 6 TOP 3 | MODE 3 TOP 3": 26,
            "TOMORROW'S PICKS - BREAKOUT": 27,
            "TOMORROW'S PICKS - BREAKOUT | TOMORROW'S PICKS - MOMENTUM": 28,
            "TOMORROW'S PICKS - INTRADAY": 29,
            "TOMORROW'S PICKS - INTRADAY | TOMORROW'S PICKS - SWING": 30,
            "TOMORROW'S PICKS - MOMENTUM": 31,
            "TOMORROW'S PICKS - RELAX": 32,
            "TOMORROW'S PICKS - SWING": 33,
            "TOMORROW'S PICKS - SWING | TOMORROW'S PICKS - RELAX": 34
          },
          "import_category": {
            "UNKNOWN": 0,
            "BREAKOUT": 1,
            "BREAKOUT PULSE": 2,
            "BREAKOUT PULSE | SWING | INTRADAY": 3,
            "BREAKOUT | MOMENTUM": 4,
            "INTRADAY": 5,
            "INTRADAY | BREAKOUT PULSE": 6,
            "INTRADAY | BREAKOUT PULSE | SWING": 7,
            "INTRADAY | RELAX": 8,
            "INTRADAY | SWING": 9,
            "MASTER RANKING": 10,
            "MOMENTUM": 11,
            "MOMENTUM | BREAKOUT PULSE": 12,
            "RELAX": 13,
            "RELAX | MOMENTUM": 14,
            "RELAX | SWING": 15,
            "RELAX | SWING | INTRADAY": 16,
            "RELAX | SWING | MOMENTUM": 17,
            "SWING": 18,
            "SWING | INTRADAY": 19,
            "SWING | INTRADAY | BREAKOUT PULSE": 20,
            "SWING | INTRADAY | RELAX": 21,
            "SWING | MOMENTUM": 22,
            "SWING | RELAX": 23
          },
          "strategy_strip": {
            "UNKNOWN": 0,
            "BREAKOUT": 1,
            "INTRADAY": 2,
            "MOMENTUM": 3,
            "RELAX": 4,
            "SWING": 5
          },
          "source_mode": {
            "UNKNOWN": 0,
            "AI": 1,
            "MANUAL": 2
          },
          "trap_risk": {
            "UNKNOWN": 0,
            "HIGH": 1,
            "LOW": 2,
            "MEDIUM": 3
          },
          "market_bias": {
            "UNKNOWN": 0,
            "BEARISH BIAS": 1,
            "SIDEWAYS / NO EDGE": 2
          },
          "regime": {
            "UNKNOWN": 0,
            "HIGH VOLATILITY / CHOPPY": 1,
            "RANGING": 2,
            "TRENDING DOWN": 3
          },
          "sector": {
            "UNKNOWN": 0,
            "AUTO": 1,
            "BANKING": 2,
            "CAPITAL_GOODS": 3,
            "CHEMICAL": 4,
            "CONSUMER_DURABLES": 5,
            "DEFENCE": 6,
            "ENERGY": 7,
            "FMCG": 8,
            "INFRA": 9,
            "IT": 10,
            "METAL": 11,
            "NBFC_FINANCE": 12,
            "PHARMA": 13,
            "PSU": 14,
            "RAILWAY": 15,
            "REALTY": 16,
            "TELECOM": 17,
            "UNMAPPED": 18
          }
        }
      },
      "mode_models": {
        "by_mode": {
          "1": {
            "mode": 1,
            "trained": true,
            "samples": 259,
            "accuracy_pct": 55.77,
            "suppressed": false,
            "suppression_factor": 1.0,
            "message": "trained",
            "validated": 0,
            "recent_accuracy_pct": null,
            "ensemble_weight": 0.5577000000000001
          },
          "2": {
            "mode": 2,
            "trained": true,
            "samples": 1320,
            "accuracy_pct": 0.0,
            "suppressed": false,
            "suppression_factor": 1.0,
            "message": "trained",
            "validated": 1,
            "recent_accuracy_pct": 0.0,
            "ensemble_weight": 0.15
          },
          "3": {
            "mode": 3,
            "trained": true,
            "samples": 887,
            "accuracy_pct": 56.34,
            "suppressed": false,
            "suppression_factor": 1.0,
            "message": "trained",
            "validated": 4253,
            "recent_accuracy_pct": 75.0,
            "ensemble_weight": 0.5634
          },
          "4": {
            "mode": 4,
            "trained": true,
            "samples": 265,
            "accuracy_pct": 37.21,
            "suppressed": true,
            "suppression_factor": 0.5,
            "message": "trained",
            "validated": 43,
            "recent_accuracy_pct": 35.0,
            "ensemble_weight": 0.18605
          },
          "5": {
            "mode": 5,
            "trained": true,
            "samples": 268,
            "accuracy_pct": 51.02,
            "suppressed": false,
            "suppression_factor": 1.0,
            "message": "trained",
            "validated": 539,
            "recent_accuracy_pct": 65.0,
            "ensemble_weight": 0.5102
          },
          "6": {
            "mode": 6,
            "trained": true,
            "samples": 596,
            "accuracy_pct": 50.59,
            "suppressed": false,
            "suppression_factor": 1.0,
            "message": "trained",
            "validated": 1022,
            "recent_accuracy_pct": 75.0,
            "ensemble_weight": 0.5059
          },
          "7": {
            "mode": 7,
            "trained": true,
            "samples": 54,
            "accuracy_pct": 44.97,
            "suppressed": true,
            "suppression_factor": 0.5,
            "message": "trained",
            "validated": 776,
            "recent_accuracy_pct": 45.0,
            "ensemble_weight": 0.22485
          }
        },
        "best_mode": {
          "mode": 3,
          "accuracy_pct": 56.34
        },
        "worst_mode": {
          "mode": 2,
          "accuracy_pct": 0.0
        },
        "message": "Mode1=55.8% | Mode2=0.0% | Mode3=56.3% | Mode4=37.2% | Mode5=51.0% | Mode6=50.6% | Mode7=45.0%"
      },
      "sector_model": {
        "by_sector": {},
        "best_sector": "",
        "worst_sector": ""
      },
      "weights": {
        "processed": 0,
        "report": [
          {
            "Signal": "ema_slope",
            "Observations": 0,
            "Win Rate": 50.0,
            "Static Weight": 10.0,
            "Dynamic Weight": 10.0,
            "\u0394 Weight": 0.0
          },
          {
            "Signal": "price_vs_ema",
            "Observations": 0,
            "Win Rate": 50.0,
            "Static Weight": 8.0,
            "Dynamic Weight": 8.0,
            "\u0394 Weight": 0.0
          },
          {
            "Signal": "candle_direction",
            "Observations": 0,
            "Win Rate": 50.0,
            "Static Weight": 10.0,
            "Dynamic Weight": 10.0,
            "\u0394 Weight": 0.0
          },
          {
            "Signal": "body_strength",
            "Observations": 0,
            "Win Rate": 50.0,
            "Static Weight": 7.0,
            "Dynamic Weight": 7.0,
            "\u0394 Weight": 0.0
          },
          {
            "Signal": "consecutive",
            "Observations": 0,
            "Win Rate": 50.0,
            "Static Weight": 7.0,
            "Dynamic Weight": 7.0,
            "\u0394 Weight": 0.0
          },
          {
            "Signal": "volume_confirm",
            "Observations": 0,
            "Win Rate": 50.0,
            "Static Weight": 10.0,
            "Dynamic Weight": 10.0,
            "\u0394 Weight": 0.0
          },
          {
            "Signal": "volatility",
            "Observations": 0,
            "Win Rate": 50.0,
            "Static Weight": 4.0,
            "Dynamic Weight": 4.0,
            "\u0394 Weight": 0.0
          },
          {
            "Signal": "momentum",
            "Observations": 0,
            "Win Rate": 50.0,
            "Static Weight": 4.0,
            "Dynamic Weight": 4.0,
            "\u0394 Weight": 0.0
          },
          {
            "Signal": "sector_strength",
            "Observations": 0,
            "Win Rate": 50.0,
            "Static Weight": 12.0,
            "Dynamic Weight": 12.0,
            "\u0394 Weight": 0.0
          },
          {
            "Signal": "bullish_pct",
            "Observations": 0,
            "Win Rate": 50.0,
            "Static Weight": 12.0,
            "Dynamic Weight": 12.0,
            "\u0394 Weight": 0.0
          },
          {
            "Signal": "money_flow",
            "Observations": 0,
            "Win Rate": 50.0,
            "Static Weight": 8.0,
            "Dynamic Weight": 8.0,
            "\u0394 Weight": 0.0
          },
          {
            "Signal": "participation",
            "Observations": 0,
            "Win Rate": 50.0,
            "Static Weight": 8.0,
            "Dynamic Weight": 8.0,
            "\u0394 Weight": 0.0
          }
        ],
        "message": "\ud83d\udcca Weights updated: sector_strength 12.0% | volatility 4.0%",
        "top_signal": {
          "signal": "sector_strength",
          "weight_pct": 12.0,
          "delta_pct": 0.0
        },
        "weakest_signal": {
          "signal": "volatility",
          "weight_pct": 4.0,
          "delta_pct": 0.0
        }
      },
      "regime": {
        "regime": "RANGE_BOUND",
        "confidence": 67.0,
        "realized_vol": 17.01,
        "adx_proxy": 14.7,
        "adjustments": {
          "ema_slope": 0.55,
          "price_vs_ema": 1.2,
          "candle_direction": 0.7,
          "body_strength": 0.8,
          "consecutive": 0.6,
          "volume_confirm": 0.9,
          "volatility": 1.3,
          "momentum": 0.65,
          "sector_strength": 1.0,
          "bullish_pct": 1.0,
          "money_flow": 1.1,
          "participation": 1.0,
          "_confidence_cap": 72.0,
          "_sideways_bias": 12.0
        },
        "message": "\ud83d\udcc8 Regime: RANGE_BOUND (conf: 67%) \u2014 weights adjusted"
      },
      "calibration": {
        "error_pct": 0.0,
        "factor": 1.0,
        "bucket_count": 0,
        "avg_confidence": 0.0,
        "actual_accuracy": 0.0,
        "message": "\ud83c\udfaf Calibration error: 0.0% | Factor applied: 1.00x"
      },
      "predictions": {
        "count": 2383,
        "df": [
          {
            "ticker": "LEMERITE",
            "direction": "Bearish",
            "confidence": 57.52,
            "raw_score": 27.47,
            "score": 27.47,
            "action": "\ud83d\udd34 Avoid",
            "hold_days": "-",
            "risk": "LOW",
            "regime": "RANGE_BOUND",
            "regime_snapshot": {
              "regime": "Range Bound",
              "description": "Mean reversion regime. Breakouts need extra confirmation.",
              "color": "#8ab4d8",
              "emoji": "\u25c6",
              "ema_aligned": false
            },
            "key_signal": "bullish_pct",
            "sector": "UNKNOWN",
            "mode_score": 0.0,
            "ml_probability": 43.16,
            "meta_model_output": 43.8,
            "mtf_alignment": 29.1,
            "regime_fit": 55.0,
            "sector_accuracy": 55.0,
            "signals": {
              "ema_slope": 0.0,
              "price_vs_ema": 0.0,
              "candle_direction": 100.0,
              "body_strength": 0.0,
              "volume_confirm": 0.0,
              "volatility": 0.0,
              "momentum": 5.04,
              "sector_strength": 29.1,
              "bullish_pct": 0.0,
              "money_flow": 50.0,
              "participation": 17.46
            },
            "weights": {
              "ema_slope": 0.061453,
              "price_vs_ema": 0.107263,
              "candle_direction": 0.078212,
              "body_strength": 0.06257,
              "consecutive": 0.046927,
              "volume_confirm": 0.100559,
              "volatility": 0.058101,
              "momentum": 0.02905,
              "sector_strength": 0.134078,
              "bullish_pct": 0.134078,
              "money_flow": 0.098324,
              "participation": 0.089385
            },
            "atr": 4.34,
            "label_tag": "Strong Breakdown",
            "indicators": {
              "RSI": 9.16,
              "Vol / Avg": 0.11,
              "5D Return (%)": -22.57,
              "20D Return (%)": -64.96,
              "\u0394 vs EMA20 (%)": -44.69,
              "\u0394 vs 20D High (%)": -67.01,
              "EMA20": 56.06,
              "EMA50": 72.29,
              "Close": 31.01
            },
            "computed_at": "2026-06-04T14:18:26"
          },
          {
            "ticker": "AVSL",
            "direction": "Bearish",
            "confidence": 50.25,
            "raw_score": 42.09,
            "score": 42.09,
            "action": "\ud83d\udd34 Avoid",
            "hold_days": "-",
            "risk": "LOW",
            "regime": "RANGE_BOUND",
            "regime_snapshot": {
              "regime": "Range Bound",
              "description": "Mean reversion regime. Breakouts need extra confirmation.",
              "color": "#8ab4d8",
              "emoji": "\u25c6",
              "ema_aligned": false
            },
            "key_signal": "bullish_pct",
            "sector": "UNKNOWN",
            "mode_score": 2.6,
            "ml_probability": 72.39,
            "meta_model_output": 43.6,
            "mtf_alignment": 59.9,
            "regime_fit": 55.0,
            "sector_accuracy": 55.0,
            "signals": {
              "ema_slope": 49.99,
              "price_vs_ema": 44.0,
              "candle_direction": 100.0,
              "body_strength": 0.0,
              "volume_confirm": 0.0,
              "volatility": 65.0,
              "momentum": 22.5,
              "sector_strength": 59.9,
              "bullish_pct": 0.0,
              "money_flow": 50.0,
              "participation": 35.94
            },
            "weights": {
              "ema_slope": 0.061453,
              "price_vs_ema": 0.107263,
              "candle_direction": 0.078212,
              "body_strength": 0.06257,
              "consecutive": 0.046927,
              "volume_confirm": 0.100559,
              "volatility": 0.058101,
              "momentum": 0.02905,
              "sector_strength": 0.134078,
              "bullish_pct": 0.134078,
              "money_flow": 0.098324,
              "participation": 0.089385
            },
            "atr": 0.0,
            "label_tag": "Range-Bound Setup",
            "indicators": {
              "RSI": 0.0,
              "Vol / Avg": 0.0,
              "5D Return (%)": 0.0,
              "20D Return (%)": 0.0,
              "\u0394 vs EMA20 (%)": -0.0,
              "\u0394 vs 20D High (%)": 0.0,
              "EMA20": 119.7,
              "EMA50": 119.87,
              "Close": 119.7
            },
            "computed_at": "2026-06-04T14:16:50"
          },
          {
            "ticker": "PARSVNATH",
            "direction": "Bearish",
            "confidence": 50.03,
            "raw_score": 29.85,
            "score": 29.85,
            "action": "\ud83d\udd34 Avoid",
            "hold_days": "-",
            "risk": "LOW",
            "regime": "RANGE_BOUND",
            "regime_snapshot": {
              "regime": "Range Bound",
              "description": "Mean reversion regime. Breakouts need extra confirmation.",
              "color": "#8ab4d8",
              "emoji": "\u25c6",
              "ema_aligned": false
            },
            "key_signal": "bullish_pct",
            "sector": "UNKNOWN",
            "mode_score": 0.0,
            "ml_probability": 47.06,
            "meta_model_output": 40.7,
            "mtf_alignment": 34.7,
            "regime_fit": 55.0,
            "sector_accuracy": 55.0,
            "signals": {
              "ema_slope": 0.0,
              "price_vs_ema": 0.0,
              "candle_direction": 100.0,
              "body_strength": 0.0,
              "volume_confirm": 0.0,
              "volatility": 38.63,
              "momentum": 11.16,
              "sector_strength": 34.7,
              "bullish_pct": 0.0,
              "money_flow": 50.0,
              "participation": 20.82
            },
            "weights": {
              "ema_slope": 0.061453,
              "price_vs_ema": 0.107263,
              "candle_direction": 0.078212,
              "body_strength": 0.06257,
              "consecutive": 0.046927,
              "volume_confirm": 0.100559,
              "volatility": 0.058101,
              "momentum": 0.02905,
              "sector_strength": 0.134078,
              "bullish_pct": 0.134078,
              "money_flow": 0.098324,
              "participation": 0.089385
            },
            "atr": 0.13,
            "label_tag": "Strong Breakdown",
            "indicators": {
              "RSI": 16.38,
              "Vol / Avg": 0.14,
              "5D Return (%)": -9.05,
              "20D Return (%)": -42.59,
              "\u0394 vs EMA20 (%)": -22.15,
              "\u0394 vs 20D High (%)": -45.29,
              "EMA20": 4.78,
              "EMA50": 6.0,
              "Close": 3.72
            },
            "computed_at": "2026-06-04T14:19:02"
          },
          {
            "ticker": "OSIAHYPER",
            "direction": "Bearish",
            "confidence": 49.71,
            "raw_score": 27.72,
            "score": 27.72,
            "action": "\ud83d\udd34 Avoid",
            "hold_days": "-",
            "risk": "LOW",
            "regime": "RANGE_BOUND",
            "regime_snapshot": {
              "regime": "Range Bound",
              "description": "Mean reversion regime. Breakouts need extra confirmation.",
              "color": "#8ab4d8",
              "emoji": "\u25c6",
              "ema_aligned": false
            },
            "key_signal": "bullish_pct",
            "sector": "UNKNOWN",
            "mode_score": 0.0,
            "ml_probability": 46.0,
            "meta_model_output": 40.6,
            "mtf_alignment": 22.5,
            "regime_fit": 55.0,
            "sector_accuracy": 55.0,
            "signals": {
              "ema_slope": 0.0,
              "price_vs_ema": 0.0,
              "candle_direction": 0.0,
              "body_strength": 42.86,
              "volume_confirm": 0.0,
              "volatility": 11.95,
              "momentum": 22.32,
              "sector_strength": 22.5,
              "bullish_pct": 0.0,
              "money_flow": 34.37,
              "participation": 13.5
            },
            "weights": {
              "ema_slope": 0.061453,
              "price_vs_ema": 0.107263,
              "candle_direction": 0.078212,
              "body_strength": 0.06257,
              "consecutive": 0.046927,
              "volume_confirm": 0.100559,
              "volatility": 0.058101,
              "momentum": 0.02905,
              "sector_strength": 0.134078,
              "bullish_pct": 0.134078,
              "money_flow": 0.098324,
              "participation": 0.089385
            },
            "atr": 0.25,
            "label_tag": "Strong Breakdown",
            "indicators": {
              "RSI": 31.72,
              "Vol / Avg": 0.48,
              "5D Return (%)": -7.83,
              "20D Return (%)": -36.96,
              "\u0394 vs EMA20 (%)": -14.82,
              "\u0394 vs 20D High (%)": -33.65,
              "EMA20": 4.14,
              "EMA50": 5.31,
              "Close": 3.53
            },
            "computed_at": "2026-06-04T14:18:59"
          },
          {
            "ticker": "RETAIL",
            "direction": "Bearish",
            "confidence": 49.54,
            "raw_score": 29.16,
            "score": 29.16,
            "action": "\ud83d\udd34 Avoid",
            "hold_days": "-",
            "risk": "LOW",
            "regime": "RANGE_BOUND",
            "regime_snapshot": {
              "regime": "Range Bound",
              "description": "Mean reversion regime. Breakouts need extra confirmation.",
              "color": "#8ab4d8",
              "emoji": "\u25c6",
              "ema_aligned": false
            },
            "key_signal": "price_vs_ema",
            "sector": "UNKNOWN",
            "mode_score": 18.85,
            "ml_probability": 20.76,
            "meta_model_output": 33.3,
            "mtf_alignment": 38.6,
            "regime_fit": 55.0,
            "sector_accuracy": 55.0,
            "signals": {
              "ema_slope": 30.33,
              "price_vs_ema": 0.0,
              "candle_direction": 0.0,
              "body_strength": 90.26,
              "volume_confirm": 100.0,
              "volatility": 0.0,
              "momentum": 20.72,
              "sector_strength": 38.6,
              "bullish_pct": 20.0,
              "money_flow": 25.0,
              "participation": 63.16
            },
            "weights": {
              "ema_slope": 0.061453,
              "price_vs_ema": 0.107263,
              "candle_direction": 0.078212,
              "body_strength": 0.06257,
              "consecutive": 0.046927,
              "volume_confirm": 0.100559,
              "volatility": 0.058101,
              "momentum": 0.02905,
              "sector_strength": 0.134078,
              "bullish_pct": 0.134078,
              "money_flow": 0.098324,
              "participation": 0.089385
            },
            "atr": 2.07,
            "label_tag": "Strong Breakdown",
            "indicators": {
              "RSI": 37.68,
              "Vol / Avg": 16.38,
              "5D Return (%)": -11.8,
              "20D Return (%)": -13.68,
              "\u0394 vs EMA20 (%)": -9.91,
              "\u0394 vs 20D High (%)": -14.33,
              "EMA20": 20.17,
              "EMA50": 20.58,
              "Close": 18.17
            },
            "computed_at": "2026-06-04T14:19:19"
          },
          {
            "ticker": "COMFINTE",
            "direction": "Bearish",
            "confidence": 48.77,
            "raw_score": 30.55,
            "score": 30.55,
            "action": "\ud83d\udd34 Avoid",
            "hold_days": "-",
            "risk": "LOW",
            "regime": "RANGE_BOUND",
            "regime_snapshot": {
              "regime": "Range Bound",
              "description": "Mean reversion regime. Breakouts need extra confirmation.",
              "color": "#8ab4d8",
              "emoji": "\u25c6",
              "ema_aligned": false
            },
            "key_signal": "price_vs_ema",
            "sector": "UNKNOWN",
            "mode_score": 1.25,
            "ml_probability": 45.71,
            "meta_model_output": 40.3,
            "mtf_alignment": 38.7,
            "regime_fit": 55.0,
            "sector_accuracy": 55.0,
            "signals": {
              "ema_slope": 0.0,
              "price_vs_ema": 0.0,
              "candle_direction": 0.0,
              "body_strength": 94.74,
              "volume_confirm": 0.0,
              "volatility": 15.55,
              "momentum": 48.35,
              "sector_strength": 38.7,
              "bullish_pct": 20.0,
              "money_flow": 25.0,
              "participation": 23.22
            },
            "weights": {
              "ema_slope": 0.061453,
              "price_vs_ema": 0.107263,
              "candle_direction": 0.078212,
              "body_strength": 0.06257,
              "consecutive": 0.046927,
              "volume_confirm": 0.100559,
              "volatility": 0.058101,
              "momentum": 0.02905,
              "sector_strength": 0.134078,
              "bullish_pct": 0.134078,
              "money_flow": 0.098324,
              "participation": 0.089385
            },
            "atr": 0.4,
            "label_tag": "Strong Breakdown",
            "indicators": {
              "RSI": 42.26,
              "Vol / Avg": 0.12,
              "5D Return (%)": 1.16,
              "20D Return (%)": -15.93,
              "\u0394 vs EMA20 (%)": -8.85,
              "\u0394 vs 20D High (%)": -28.75,
              "EMA20": 6.71,
              "EMA50": 7.1,
              "Close": 6.12
            },
            "computed_at": "2026-06-04T14:17:08"
          },
          {
            "ticker": "GTECJAINX",
            "direction": "Sideways",
            "confidence": 47.98,
            "raw_score": 50.3,
            "score": 50.3,
            "action": "\ud83d\udd34 Avoid",
            "hold_days": "-",
            "risk": "HIGH",
            "regime": "RANGE_BOUND",
            "regime_snapshot": {
              "regime": "Range Bound",
              "description": "Mean reversion regime. Breakouts need extra confirmation.",
              "color": "#8ab4d8",
              "emoji": "\u25c6",
              "ema_aligned": true
            },
            "key_signal": "bullish_pct",
            "sector": "UNKNOWN",
            "mode_score": 20.47,
            "ml_probability": 61.48,
            "meta_model_output": 38.1,
            "mtf_alignment": 91.2,
            "regime_fit": 55.0,
            "sector_accuracy": 55.0,
            "signals": {
              "ema_slope": 100.0,
              "price_vs_ema": 100.0,
              "candle_direction": 100.0,
              "body_strength": 100.0,
              "volume_confirm": 72.31,
              "volatility": 8.8,
              "momentum": 89.23,
              "sector_strength": 91.2,
              "bullish_pct": 100.0,
              "money_flow": 73.54,
              "participation": 83.64
            },
            "weights": {
              "ema_slope": 0.061453,
              "price_vs_ema": 0.107263,
              "candle_direction": 0.078212,
              "body_strength": 0.06257,
              "consecutive": 0.046927,
              "volume_confirm": 0.100559,
              "volatility": 0.058101,
              "momentum": 0.02905,
              "sector_strength": 0.134078,
              "bullish_pct": 0.134078,
              "money_flow": 0.098324,
              "participation": 0.089385
            },
            "atr": 2.38,
            "label_tag": "Strong Momentum",
            "indicators": {
              "RSI": 80.42,
              "Vol / Avg": 1.78,
              "5D Return (%)": 78.59,
              "20D Return (%)": 61.32,
              "\u0394 vs EMA20 (%)": 49.07,
              "\u0394 vs 20D High (%)": 0.0,
              "EMA20": 21.27,
              "EMA50": 20.28,
              "Close": 31.7
            },
            "computed_at": "2026-06-04T14:17:46"
          },
          {
            "ticker": "KIRANVYPAR",
            "direction": "Bearish",
            "confidence": 47.8,
            "raw_score": 31.15,
            "score": 31.15,
            "action": "\ud83d\udd34 Avoid",
            "hold_days": "-",
            "risk": "LOW",
            "regime": "RANGE_BOUND",
            "regime_snapshot": {
              "regime": "Range Bound",
              "description": "Mean reversion regime. Breakouts need extra confirmation.",
              "color": "#8ab4d8",
              "emoji": "\u25c6",
              "ema_aligned": false
            },
            "key_signal": "bullish_pct",
            "sector": "UNKNOWN",
            "mode_score": 0.0,
            "ml_probability": 47.94,
            "meta_model_output": 40.9,
            "mtf_alignment": 40.9,
            "regime_fit": 55.0,
            "sector_accuracy": 55.0,
            "signals": {
              "ema_slope": 0.0,
              "price_vs_ema": 0.0,
              "candle_direction": 0.0,
              "body_strength": 89.49,
              "volume_confirm": 2.05,
              "volatility": 1.94,
              "momentum": 24.15,
              "sector_strength": 40.9,
              "bullish_pct": 0.0,
              "money_flow": 41.92,
              "participation": 25.36
            },
            "weights": {
              "ema_slope": 0.061453,
              "price_vs_ema": 0.107263,
              "candle_direction": 0.078212,
              "body_strength": 0.06257,
              "consecutive": 0.046927,
              "volume_confirm": 0.100559,
              "volatility": 0.058101,
              "momentum": 0.02905,
              "sector_strength": 0.134078,
              "bullish_pct": 0.134078,
              "money_flow": 0.098324,
              "participation": 0.089385
            },
            "atr": 12.77,
            "label_tag": "Strong Breakdown",
            "indicators": {
              "RSI": 33.07,
              "Vol / Avg": 0.73,
              "5D Return (%)": -7.35,
              "20D Return (%)": -22.1,
              "\u0394 vs EMA20 (%)": -11.88,
              "\u0394 vs 20D High (%)": -23.23,
              "EMA20": 172.33,
              "EMA50": 181.61,
              "Close": 151.86
            },
            "computed_at": "2026-06-04T14:18:13"
          },
          {
            "ticker": "3BBLACKBIO",
            "direction": "Bearish",
            "confidence": 47.57,
            "raw_score": 30.42,
            "score": 30.42,
            "action": "\ud83d\udd34 Avoid",
            "hold_days": "-",
            "risk": "LOW",
            "regime": "RANGE_BOUND",
            "regime_snapshot": {
              "regime": "Range Bound",
              "description": "Mean reversion regime. Breakouts need extra confirmation.",
              "color": "#8ab4d8",
              "emoji": "\u25c6",
              "ema_aligned": false
            },
            "key_signal": "price_vs_ema",
            "sector": "UNKNOWN",
            "mode_score": 3.34,
            "ml_probability": 45.86,
            "meta_model_output": 39.8,
            "mtf_alignment": 34.7,
            "regime_fit": 55.0,
            "sector_accuracy": 55.0,
            "signals": {
              "ema_slope": 0.0,
              "price_vs_ema": 0.62,
              "candle_direction": 0.0,
              "body_strength": 37.34,
              "volume_confirm": 0.0,
              "volatility": 21.01,
              "momentum": 33.01,
              "sector_strength": 34.7,
              "bullish_pct": 20.0,
              "money_flow": 31.74,
              "participation": 20.82
            },
            "weights": {
              "ema_slope": 0.061453,
              "price_vs_ema": 0.107263,
              "candle_direction": 0.078212,
              "body_strength": 0.06257,
              "consecutive": 0.046927,
              "volume_confirm": 0.100559,
              "volatility": 0.058101,
              "momentum": 0.02905,
              "sector_strength": 0.134078,
              "bullish_pct": 0.134078,
              "money_flow": 0.098324,
              "participation": 0.089385
            },
            "atr": 66.09,
            "label_tag": "Strong Breakdown",
            "indicators": {
              "RSI": 50.85,
              "Vol / Avg": 0.39,
              "5D Return (%)": -7.76,
              "20D Return (%)": -14.5,
              "\u0394 vs EMA20 (%)": -7.23,
              "\u0394 vs 20D High (%)": -17.85,
              "EMA20": 1214.73,
              "EMA50": 1257.22,
              "Close": 1126.9
            },
            "computed_at": "2026-06-04T14:16:33"
          },
          {
            "ticker": "TECHNOE",
            "direction": "Bearish",
            "confidence": 46.49,
            "raw_score": 29.13,
            "score": 29.13,
            "action": "\ud83d\udd34 Avoid",
            "hold_days": "-",
            "risk": "LOW",
            "regime": "RANGE_BOUND",
            "regime_snapshot": {
              "regime": "Range Bound",
              "description": "Mean reversion regime. Breakouts need extra confirmation.",
              "color": "#8ab4d8",
              "emoji": "\u25c6",
              "ema_aligned": false
            },
            "key_signal": "bullish_pct",
            "sector": "UNKNOWN",
            "mode_score": 0.0,
            "ml_probability": 47.06,
            "meta_model_output": 40.7,
            "mtf_alignment": 24.5,
            "regime_fit": 55.0,
            "sector_accuracy": 55.0,
            "signals": {
              "ema_slope": 0.0,
              "price_vs_ema": 0.0,
              "candle_direction": 0.0,
              "body_strength": 78.57,
              "volume_confirm": 11.73,
              "volatility": 23.66,
              "momentum": 27.72,
              "sector_strength": 24.5,
              "bullish_pct": 0.0,
              "money_flow": 46.28,
              "participation": 19.39
            },
            "weights": {
              "ema_slope": 0.061453,
              "price_vs_ema": 0.107263,
              "candle_direction": 0.078212,
              "body_strength": 0.06257,
              "consecutive": 0.046927,
              "volume_confirm": 0.100559,
              "volatility": 0.058101,
              "momentum": 0.02905,
              "sector_strength": 0.134078,
              "bullish_pct": 0.134078,
              "money_flow": 0.098324,
              "participation": 0.089385
            },
            "atr": 55.73,
            "label_tag": "Strong Breakdown",
            "indicators": {
              "RSI": 32.99,
              "Vol / Avg": 0.88,
              "5D Return (%)": -5.74,
              "20D Return (%)": -21.15,
              "\u0394 vs EMA20 (%)": -11.98,
              "\u0394 vs 20D High (%)": -26.37,
              "EMA20": 1148.54,
              "EMA50": 1163.96,
              "Close": 1011.0
            },
            "computed_at": "2026-06-04T14:20:03"
          },
          {
            "ticker": "VPRPL",
            "direction": "Bearish",
            "confidence": 46.21,
            "raw_score": 29.7,
            "score": 29.7,
            "action": "\ud83d\udd34 Avoid",
            "hold_days": "-",
            "risk": "LOW",
            "regime": "RANGE_BOUND",
            "regime_snapshot": {
              "regime": "Range Bound",
              "description": "Mean reversion regime. Breakouts need extra confirmation.",
              "color": "#8ab4d8",
              "emoji": "\u25c6",
              "ema_aligned": false
            },
            "key_signal": "bullish_pct",
            "sector": "UNKNOWN",
            "mode_score": 0.0,
            "ml_probability": 46.96,
            "meta_model_output": 40.7,
            "mtf_alignment": 27.1,
            "regime_fit": 55.0,
            "sector_accuracy": 55.0,
            "signals": {
              "ema_slope": 0.0,
              "price_vs_ema": 0.0,
              "candle_direction": 100.0,
              "body_strength": 0.0,
              "volume_confirm": 11.05,
              "volatility": 26.21,
              "momentum": 15.84,
              "sector_strength": 27.1,
              "bullish_pct": 0.0,
              "money_flow": 50.0,
              "participation": 20.68
            },
            "weights": {
              "ema_slope": 0.061453,
              "price_vs_ema": 0.107263,
              "candle_direction": 0.078212,
              "body_strength": 0.06257,
              "consecutive": 0.046927,
              "volume_confirm": 0.100559,
              "volatility": 0.058101,
              "momentum": 0.02905,
              "sector_strength": 0.134078,
              "bullish_pct": 0.134078,
              "money_flow": 0.098324,
              "participation": 0.089385
            },
            "atr": 1.68,
            "label_tag": "Strong Breakdown",
            "indicators": {
              "RSI": 28.8,
              "Vol / Avg": 0.87,
              "5D Return (%)": -19.66,
              "20D Return (%)": -29.56,
              "\u0394 vs EMA20 (%)": -16.31,
              "\u0394 vs 20D High (%)": -27.93,
              "EMA20": 38.86,
              "EMA50": 40.66,
              "Close": 32.52
            },
            "computed_at": "2026-06-04T14:20:18"
          },
          {
            "ticker": "RMC",
            "direction": "Bearish",
            "confidence": 46.09,
            "raw_score": 33.07,
            "score": 33.07,
            "action": "\ud83d\udd34 Avoid",
            "hold_days": "-",
            "risk": "LOW",
            "regime": "RANGE_BOUND",
            "regime_snapshot": {
              "regime": "Range Bound",
              "description": "Mean reversion regime. Breakouts need extra confirmation.",
              "color": "#8ab4d8",
              "emoji": "\u25c6",
              "ema_aligned": false
            },
            "key_signal": "price_vs_ema",
            "sector": "UNKNOWN",
            "mode_score": 7.47,
            "ml_probability": 46.56,
            "meta_model_output": 39.0,
            "mtf_alignment": 44.9,
            "regime_fit": 55.0,
            "sector_accuracy": 55.0,
            "signals": {
              "ema_slope": 0.0,
              "price_vs_ema": 0.0,
              "candle_direction": 0.0,
              "body_strength": 22.15,
              "volume_confirm": 64.26,
              "volatility": 19.57,
              "momentum": 13.38,
              "sector_strength": 44.9,
              "bullish_pct": 20.0,
              "money_flow": 30.08,
              "participation": 52.64
            },
            "weights": {
              "ema_slope": 0.061453,
              "price_vs_ema": 0.107263,
              "candle_direction": 0.078212,
              "body_strength": 0.06257,
              "consecutive": 0.046927,
              "volume_confirm": 0.100559,
              "volatility": 0.058101,
              "momentum": 0.02905,
              "sector_strength": 0.134078,
              "bullish_pct": 0.134078,
              "money_flow": 0.098324,
              "participation": 0.089385
            },
            "atr": 19.18,
            "label_tag": "Strong Breakdown",
            "indicators": {
              "RSI": 24.33,
              "Vol / Avg": 1.66,
              "5D Return (%)": -20.97,
              "20D Return (%)": -31.39,
              "\u0394 vs EMA20 (%)": -19.35,
              "\u0394 vs 20D High (%)": -31.65,
              "EMA20": 392.6,
              "EMA50": 411.56,
              "Close": 316.65
            },
            "computed_at": "2026-06-04T14:19:21"
          }
        ],
        "message": "\ud83d\udd2e Tomorrow predictions: 2383 tickers computed"
      },
      "error": ""
    }
  },
  "signal_weight_status": {
    "processed": 0,
    "top_signal": "sector_strength",
    "top_weight": 12.0,
    "weakest_signal": "volatility",
    "weakest_weight": 4.0,
    "report_rows": [
      {
        "Signal": "ema_slope",
        "Observations": 0,
        "Win Rate": 50.0,
        "Static Weight": 10.0,
        "Dynamic Weight": 10.0,
        "\u0394 Weight": 0.0
      },
      {
        "Signal": "price_vs_ema",
        "Observations": 0,
        "Win Rate": 50.0,
        "Static Weight": 8.0,
        "Dynamic Weight": 8.0,
        "\u0394 Weight": 0.0
      },
      {
        "Signal": "candle_direction",
        "Observations": 0,
        "Win Rate": 50.0,
        "Static Weight": 10.0,
        "Dynamic Weight": 10.0,
        "\u0394 Weight": 0.0
      },
      {
        "Signal": "body_strength",
        "Observations": 0,
        "Win Rate": 50.0,
        "Static Weight": 7.0,
        "Dynamic Weight": 7.0,
        "\u0394 Weight": 0.0
      },
      {
        "Signal": "consecutive",
        "Observations": 0,
        "Win Rate": 50.0,
        "Static Weight": 7.0,
        "Dynamic Weight": 7.0,
        "\u0394 Weight": 0.0
      },
      {
        "Signal": "volume_confirm",
        "Observations": 0,
        "Win Rate": 50.0,
        "Static Weight": 10.0,
        "Dynamic Weight": 10.0,
        "\u0394 Weight": 0.0
      },
      {
        "Signal": "volatility",
        "Observations": 0,
        "Win Rate": 50.0,
        "Static Weight": 4.0,
        "Dynamic Weight": 4.0,
        "\u0394 Weight": 0.0
      },
      {
        "Signal": "momentum",
        "Observations": 0,
        "Win Rate": 50.0,
        "Static Weight": 4.0,
        "Dynamic Weight": 4.0,
        "\u0394 Weight": 0.0
      },
      {
        "Signal": "sector_strength",
        "Observations": 0,
        "Win Rate": 50.0,
        "Static Weight": 12.0,
        "Dynamic Weight": 12.0,
        "\u0394 Weight": 0.0
      },
      {
        "Signal": "bullish_pct",
        "Observations": 0,
        "Win Rate": 50.0,
        "Static Weight": 12.0,
        "Dynamic Weight": 12.0,
        "\u0394 Weight": 0.0
      },
      {
        "Signal": "money_flow",
        "Observations": 0,
        "Win Rate": 50.0,
        "Static Weight": 8.0,
        "Dynamic Weight": 8.0,
        "\u0394 Weight": 0.0
      },
      {
        "Signal": "participation",
        "Observations": 0,
        "Win Rate": 50.0,
        "Static Weight": 8.0,
        "Dynamic Weight": 8.0,
        "\u0394 Weight": 0.0
      }
    ]
  }
}